{
  "2025": {
    "10-12": {
      "views": 48,
      "unique_visitors": 8,
      "clones": 7,
      "unique_cloners": 7,
      "timestamp": "2025-10-12T09:19:05.593318+00:00"
    },
    "09-29": {
      "views": 21,
      "unique_visitors": 3,
      "clones": 1,
      "unique_cloners": 1,
      "timestamp": "2025-10-12T09:19:06.434572+00:00"
    },
    "09-30": {
      "views": 7,
      "unique_visitors": 2,
      "clones": 2,
      "unique_cloners": 2,
      "timestamp": "2025-10-12T09:19:06.434583+00:00"
    },
    "10-01": {
      "views": 7,
      "unique_visitors": 1,
      "clones": 0,
      "unique_cloners": 0,
      "timestamp": "2025-10-12T09:19:06.434526+00:00"
    },
    "10-06": {
      "views": 12,
      "unique_visitors": 1,
      "clones": 0,
      "unique_cloners": 0,
      "timestamp": "2025-10-12T09:19:06.434538+00:00"
    },
    "10-07": {
      "views": 1,
      "unique_visitors": 1,
      "clones": 0,
      "unique_cloners": 0,
      "timestamp": "2025-10-12T09:19:06.434549+00:00"
    },
    "09-28": {
      "views": 0,
      "unique_visitors": 0,
      "clones": 1,
      "unique_cloners": 1,
      "timestamp": "2025-10-12T09:19:06.434560+00:00"
    },
    "10-03": {
      "views": 0,
      "unique_visitors": 0,
      "clones": 1,
      "unique_cloners": 1,
      "timestamp": "2025-10-12T09:19:06.434594+00:00"
    },
    "10-04": {
      "views": 0,
      "unique_visitors": 0,
      "clones": 1,
      "unique_cloners": 1,
      "timestamp": "2025-10-12T09:19:06.434605+00:00"
    },
    "10-10": {
      "views": 0,
      "unique_visitors": 0,
      "clones": 1,
      "unique_cloners": 1,
      "timestamp": "2025-10-12T09:19:06.434616+00:00"
    }
  }
}